py_speedtest/__init__.py
py_speedtest/client/__init__.py
py_speedtest/client/client.py
py_speedtest/exceptions/__init__.py
py_speedtest/exceptions/speedtest_error.py
py_speedtest/models/__init__.py
py_speedtest/models/bandwidth.py
py_speedtest/models/hosted_result.py
py_speedtest/models/interface.py
py_speedtest/models/log_entry.py
py_speedtest/models/ping.py
py_speedtest/models/result.py
py_speedtest/models/server.py
py_speedtest/models/speedtest_run.py
py_speedtest_cli-0.0.2.dist-info/LICENSE
py_speedtest_cli-0.0.2.dist-info/METADATA
py_speedtest_cli-0.0.2.dist-info/WHEEL
py_speedtest_cli-0.0.2.dist-info/top_level.txt
py_speedtest_cli-0.0.2.dist-info/RECORD
