Metadata-Version: 2.1
Name: py-speedtest-cli
Version: 0.0.2
Summary: Simple Speedtest.net CLI Python client
Home-page: https://github.com/amickael/py-speedtest
Author: Andrew Mickael
Author-email: andrew.mickael@gmail.com
License: UNKNOWN
Platform: UNKNOWN
Classifier: Programming Language :: Python :: 3
Classifier: License :: OSI Approved :: MIT License
Classifier: Operating System :: OS Independent
Requires-Python: >=3.7
License-File: LICENSE
Requires-Dist: pydantic (==1.9.0)
